docling_jobkit/__init__.py
docling_jobkit/py.typed
docling_jobkit/cli/__init__.py
docling_jobkit/cli/local.py
docling_jobkit/cli/multiproc.py
docling_jobkit/connectors/__init__.py
docling_jobkit/connectors/google_drive_helper.py
docling_jobkit/connectors/google_drive_source_processor.py
docling_jobkit/connectors/google_drive_target_processor.py
docling_jobkit/connectors/http_source_processor.py
docling_jobkit/connectors/local_path_source_processor.py
docling_jobkit/connectors/local_path_target_processor.py
docling_jobkit/connectors/s3_helper.py
docling_jobkit/connectors/s3_source_processor.py
docling_jobkit/connectors/s3_target_processor.py
docling_jobkit/connectors/source_processor.py
docling_jobkit/connectors/source_processor_factory.py
docling_jobkit/connectors/target_processor.py
docling_jobkit/connectors/target_processor_factory.py
docling_jobkit/convert/__init__.py
docling_jobkit/convert/chunking.py
docling_jobkit/convert/manager.py
docling_jobkit/convert/results.py
docling_jobkit/convert/results_processor.py
docling_jobkit/datamodel/__init__.py
docling_jobkit/datamodel/callback.py
docling_jobkit/datamodel/chunking.py
docling_jobkit/datamodel/convert.py
docling_jobkit/datamodel/google_drive_coords.py
docling_jobkit/datamodel/http_inputs.py
docling_jobkit/datamodel/result.py
docling_jobkit/datamodel/s3_coords.py
docling_jobkit/datamodel/task.py
docling_jobkit/datamodel/task_meta.py
docling_jobkit/datamodel/task_sources.py
docling_jobkit/datamodel/task_targets.py
docling_jobkit/kfp_pipeline/__init__.py
docling_jobkit/kfp_pipeline/docling-s3in-s3out.yaml
docling_jobkit/kfp_pipeline/docling_s3in_s3out.py
docling_jobkit/kfp_pipeline/docling_s3in_s3out_with_infer.py
docling_jobkit/kfp_pipeline/docling_s3in_s3out_with_infer.yaml
docling_jobkit/orchestrators/__init__.py
docling_jobkit/orchestrators/base_notifier.py
docling_jobkit/orchestrators/base_orchestrator.py
docling_jobkit/orchestrators/kfp/__init__.py
docling_jobkit/orchestrators/kfp/kfp_pipeline.py
docling_jobkit-1.9.1.dist-info/METADATA
docling_jobkit-1.9.1.dist-info/WHEEL
docling_jobkit-1.9.1.dist-info/entry_points.txt
docling_jobkit-1.9.1.dist-info/licenses/LICENSE
docling_jobkit-1.9.1.dist-info/RECORD
