Metadata-Version: 2.4
Name: docling-jobkit
Version: 1.9.1
Summary: Running a distributed job processing documents with Docling.
Project-URL: Homepage, https://github.com/docling-project/docling-jobkit
Project-URL: Documentation, https://docling-project.github.io/docling/usage/jobkit/
Project-URL: Repository, https://github.com/docling-project/docling-jobkit
Project-URL: Issues, https://github.com/docling-project/docling-jobkit/issues
Project-URL: Changelog, https://github.com/docling-project/docling-jobkit/blob/main/CHANGELOG.md
Author-email: Michele Dolfi <dol@zurich.ibm.com>, Viktor Kuropiatnyk <vku@zurich.ibm.com>, Tiago Santana <Tiago.Santana@ibm.com>, Cesar Berrospi Ramis <ceb@zurich.ibm.com>, Panos Vagenas <pva@zurich.ibm.com>, Christoph Auer <cau@zurich.ibm.com>, Peter Staar <taa@zurich.ibm.com>
Maintainer-email: Michele Dolfi <dol@zurich.ibm.com>, Cesar Berrospi Ramis <ceb@zurich.ibm.com>, Panos Vagenas <pva@zurich.ibm.com>, Christoph Auer <cau@zurich.ibm.com>, Peter Staar <taa@zurich.ibm.com>
License-Expression: MIT
License-File: LICENSE
Classifier: Development Status :: 5 - Production/Stable
Classifier: Intended Audience :: Developers
Classifier: Operating System :: OS Independent
Classifier: Programming Language :: Python :: 3
Classifier: Programming Language :: Python :: 3.10
Classifier: Programming Language :: Python :: 3.11
Classifier: Programming Language :: Python :: 3.12
Classifier: Programming Language :: Python :: 3.13
Classifier: Programming Language :: Python :: 3.14
Classifier: Topic :: Scientific/Engineering :: Artificial Intelligence
Classifier: Topic :: Scientific/Engineering :: Information Analysis
Classifier: Topic :: Software Development :: Build Tools
Classifier: Topic :: Software Development :: Libraries :: Python Modules
Classifier: Typing :: Typed
Requires-Python: >=3.10
Requires-Dist: boto3~=1.35
Requires-Dist: docling~=2.60
Requires-Dist: httpx<1,>=0.28
Requires-Dist: pandas~=2.2
Requires-Dist: pydantic-settings~=2.4
Requires-Dist: pydantic~=2.10
Requires-Dist: typer<1,>=0.12.5
Provides-Extra: gdrive
Requires-Dist: google-api-python-client>=2.183.0; extra == 'gdrive'
Requires-Dist: google-auth-oauthlib>=1.2.2; extra == 'gdrive'
Provides-Extra: kfp
Requires-Dist: kfp[kubernetes]>=2.10.0; extra == 'kfp'
Provides-Extra: ray
Requires-Dist: ray~=2.30; (python_version < '3.14') and extra == 'ray'
Provides-Extra: rq
Requires-Dist: msgpack~=1.1; extra == 'rq'
Requires-Dist: rq~=2.4; extra == 'rq'
Provides-Extra: vlm
Requires-Dist: docling[vlm]~=2.60; extra == 'vlm'
